pydoda/__init__.py
pydoda/category.py
pydoda/custom_category.py
pydoda/loader.py
pydoda/old.py
pydoda/py_doda.py
pydoda/sentence.py
pydoda/utils.py
pydoda/dataset/LICENSE
pydoda/dataset/README.md
pydoda/dataset/imagenet_b_darija.csv
pydoda/dataset/images/doda_logo.png
pydoda/dataset/images/video_img.png
pydoda/dataset/images/wordcloud.png
pydoda/dataset/ongoing/02.csv
pydoda/dataset/ongoing/03.csv
pydoda/dataset/ongoing/04.csv
pydoda/dataset/ongoing/05.csv
pydoda/dataset/ongoing/06.csv
pydoda/dataset/ongoing/07.csv
pydoda/dataset/ongoing/08.csv
pydoda/dataset/ongoing/09.csv
pydoda/dataset/ongoing/10.csv
pydoda/dataset/ongoing/11.csv
pydoda/dataset/ongoing/12.csv
pydoda/dataset/ongoing/15.csv
pydoda/dataset/ongoing/16.csv
pydoda/dataset/ongoing/17.csv
pydoda/dataset/ongoing/18.csv
pydoda/dataset/ongoing/19.csv
pydoda/dataset/ongoing/20.csv
pydoda/dataset/ongoing/21.csv
pydoda/dataset/ongoing/22.csv
pydoda/dataset/ongoing/23.csv
pydoda/dataset/ongoing/24.csv
pydoda/dataset/ongoing/35.csv
pydoda/dataset/ongoing/36.csv
pydoda/dataset/ongoing/37.csv
pydoda/dataset/ongoing/38.csv
pydoda/dataset/ongoing/39.csv
pydoda/dataset/ongoing/40.csv
pydoda/dataset/ongoing/41.csv
pydoda/dataset/ongoing/42.csv
pydoda/dataset/ongoing/43.csv
pydoda/dataset/ongoing/44.csv
pydoda/dataset/ongoing/45.csv
pydoda/dataset/ongoing/46.csv
pydoda/dataset/ongoing/49.csv
pydoda/dataset/ongoing/51.csv
pydoda/dataset/ongoing/59.csv
pydoda/dataset/ongoing/62.csv
pydoda/dataset/ongoing/67.csv
pydoda/dataset/ongoing/70.csv
pydoda/dataset/ongoing/71.csv
pydoda/dataset/ongoing/72.csv
pydoda/dataset/ongoing/73.csv
pydoda/dataset/ongoing/74.csv
pydoda/dataset/semantic categories/animals.csv
pydoda/dataset/semantic categories/art.csv
pydoda/dataset/semantic categories/clothes.csv
pydoda/dataset/semantic categories/colors.csv
pydoda/dataset/semantic categories/economy.csv
pydoda/dataset/semantic categories/education.csv
pydoda/dataset/semantic categories/emotions.csv
pydoda-1.2.1.dist-info/LICENSE
pydoda-1.2.1.dist-info/METADATA
pydoda-1.2.1.dist-info/WHEEL
pydoda-1.2.1.dist-info/top_level.txt
pydoda-1.2.1.dist-info/RECORD
